rundeckpy/__init__.py
rundeckpy/rd_connectors.py
rundeckpy/rd_helpers.py
rundeckpy/rd_plugin.py
rundeckpy/rundeckpy.py
rundeckpy-0.2.8.dist-info/entry_points.txt
rundeckpy-0.2.8.dist-info/WHEEL
rundeckpy-0.2.8.dist-info/METADATA
rundeckpy-0.2.8.dist-info/RECORD
