Metadata-Version: 2.1
Name: rundeckpy
Version: 0.2.8
Summary: Rundeck python plugins, helper functions and cli tool
Home-page: https://gitlab.com/labitup/rundeck/rundeckpy/-/wikis/home
License: Proprietary
Keywords: rundeck,python,plugin
Author: Thiago Takayama
Author-email: thiago@takayama.co.uk
Requires-Python: >=3.6,<4.0
Classifier: License :: Other/Proprietary License
Classifier: Programming Language :: Python :: 3
Classifier: Programming Language :: Python :: 3.6
Classifier: Programming Language :: Python :: 3.7
Classifier: Programming Language :: Python :: 3.8
Classifier: Programming Language :: Python :: 3.9
Requires-Dist: click (>=7.1.2,<8.0.0)
Requires-Dist: paramiko (>=2.7.2,<3.0.0)
Project-URL: Documentation, https://gitlab.com/labitup/rundeck/rundeckpy/-/wikis/home
Project-URL: Repository, https://gitlab.com/labitup/rundeck/rundeckpy
